TaskFlowPy/__init__.py
TaskFlowPy/storage.py
TaskFlowPy/task_manager.py
tests/__init__.py
tests/test_task_manager.py
taskflowpy-0.1.0.dist-info/LICENSE
taskflowpy-0.1.0.dist-info/METADATA
taskflowpy-0.1.0.dist-info/WHEEL
taskflowpy-0.1.0.dist-info/top_level.txt
taskflowpy-0.1.0.dist-info/RECORD
