Metadata-Version: 2.2
Name: TaskFlowPy
Version: 0.1.0
Summary: Um gerenciador de tarefas simples e eficiente para projetos Python, com suporte a JSON e SQLite.
Home-page: https://github.com/robertolima-dev/TaskFlowPy
Author: Roberto Lima
Author-email: Roberto Lima <robertolima.izphera@gmail.com>
License: MIT License
Project-URL: Source, https://github.com/robertolima-dev/TaskFlowPy
Project-URL: Tracker, https://github.com/robertolima-dev/TaskFlowPy/issues
Classifier: Programming Language :: Python :: 3
Classifier: License :: OSI Approved :: MIT License
Classifier: Operating System :: OS Independent
Requires-Python: >=3.7
License-File: LICENSE
Dynamic: author
Dynamic: home-page
Dynamic: requires-python
